Playlist_downloader/__init__.py
Playlist_downloader-0.0.5.dist-info/LICENSE
Playlist_downloader-0.0.5.dist-info/METADATA
Playlist_downloader-0.0.5.dist-info/WHEEL
Playlist_downloader-0.0.5.dist-info/top_level.txt
Playlist_downloader-0.0.5.dist-info/RECORD
